{
  "$schema": "https://mintlify.com/schema.json",
  "name": "ETRNL VAULT",
  "logo": {
    "dark": "/logo/v-white.svg",
    "light": "/logo/v-black.svg"
  },
  "favicon": "/favicon.png",
  "colors": {
    "primary": "#000000",
    "light": "#FFFFFF",
    "dark": "#0D001D",
    "background": {
      "dark": "#000000"
    },
    "anchors": {
      "from": "#303030",
      "to": "#303030"
    }
  },
  "topbarLinks": [
    {
      "name": "Support",
      "url": "mailto:support@etrnl.app"
    }
  ],
  "topbarCtaButton": {
    "name": "Dashboard",
    "url": "https://dashboard.mintlify.com"
  },
  "tabs": [
    {
      "name": "API Reference",
      "url": "api-reference"
    }
  ],
  "anchors": [
    {
      "name": "Discord",
      "icon": "discord",
      "url": "https://discord.gg/FvNtx5ga8h"
    },
    {
      "name": "Blog",
      "icon": "newspaper",
      "url": "https://blog.etrnl.app"
    }
  ],
  "navigation": [
    {
      "group": "Get Started",
      "pages": [
			"introduction",
			"nfc",
			"ntag-424-dna"
		]
    },
	{
		"group": "Examples",
		"pages": [
			"example/quickstart"
		  ]
	  },
    {
      "group": "API Documentation",
      "pages": [
		"api-reference/before-you-begin",
		"api-reference/keys"
	  ]
    },
    {
      "group": "Tag",
      "pages": [
		"api-reference/endpoints/tag/verify-authenticity"
	  ]
    },
	{
		"group": "URL Groups",
		"pages": [
		  "api-reference/endpoints/url-groups/create",
		  "api-reference/endpoints/url-groups/update",
		  "api-reference/endpoints/url-groups/get",
		  "api-reference/endpoints/url-groups/get-all",
		  "api-reference/endpoints/url-groups/delete"
		]
	  }
  ],
  "footerSocials": {
    "twitter": "https://twitter.com/etrnlvault",
	"instagram": "https://instagram.com/etrnlvault",
    "linkedin": "https://www.linkedin.com/company/mintsearch"
  },
  "api": {
	"baseUrl": "https://third-party.etrnl.app",
	"auth": {
		"method": "key"
	}
  }
}
